{"expireTime":9007200840272312000,"key":"create-remote-file-node-https://images.prismic.io/studiogurr/cc629049-3ff8-4151-9d52-43305dde3fab_Steadlight_4.jpg?auto=compress,format","val":{"last-modified":"Sat, 28 Mar 2020 18:49:35 GMT","cache-control":"public, max-age=315360000","server":"imgix","x-imgix-id":"dd242ae837a901de94b33df6817465d357f4f653","content-length":"865335","date":"Mon, 30 Mar 2020 01:21:47 GMT","connection":"close","age":"109933","accept-ranges":"bytes","content-type":"image/jpeg","access-control-allow-origin":"*","x-content-type-options":"nosniff","x-served-by":"cache-lax8629-LAX, cache-fty21380-FTY","x-cache":"MISS, HIT","vary":"Accept, User-Agent"}}