{"expireTime":9007200841012758000,"key":"create-remote-file-node-https://images.prismic.io/studiogurr/db2b1901-f9cd-4169-bc3e-9e185c153f80_Nashville+Proper_6.jpg?auto=compress,format","val":{"last-modified":"Tue, 24 Mar 2020 22:34:02 GMT","cache-control":"public, max-age=315360000","server":"imgix","x-imgix-id":"681edca5eb90d1240524a694cd9e68c901a92a07","content-length":"768391","date":"Tue, 07 Apr 2020 15:02:46 GMT","connection":"close","age":"1182524","accept-ranges":"bytes","content-type":"image/jpeg","access-control-allow-origin":"*","x-content-type-options":"nosniff","x-served-by":"cache-lax8642-LAX, cache-wdc5577-WDC","x-cache":"MISS, HIT","vary":"Accept, User-Agent"}}